{
    "include": [
        "ai_scientist",
        "tests"
    ],
    "exclude": [
        "**/__pycache__",
        "**/.pytest_cache",
        "**/.ruff_cache",
        ".conda",
        ".git"
    ],
    "pythonVersion": "3.11",
    "pythonPlatform": "Darwin",
    "typeCheckingMode": "basic",
    "reportMissingImports": "none",
    "reportMissingTypeStubs": "none",
    "reportAttributeAccessIssue": "none",
    "reportGeneralTypeIssues": "error",
    "reportOptionalSubscript": "none",
    "reportOptionalMemberAccess": "none",
    "reportOptionalCall": "none",
    "reportOptionalIterable": "none",
    "reportOptionalContextManager": "none",
    "reportOptionalOperand": "none",
    "reportUntypedFunctionDecorator": "none",
    "reportUntypedClassDecorator": "none",
    "reportUntypedBaseClass": "none",
    "reportUnknownParameterType": "none",
    "reportUnknownArgumentType": "none",
    "reportUnknownLambdaType": "none",
    "reportUnknownVariableType": "none",
    "reportUnknownMemberType": "none",
    "reportMissingParameterType": "none",
    "reportMissingTypeArgument": "none",
    "reportInvalidTypeVarUse": "error",
    "reportCallInDefaultInitializer": "none",
    "reportUnnecessaryIsInstance": "none",
    "reportUnnecessaryCast": "none",
    "reportImplicitStringConcatenation": "none",
    "reportUnusedImport": "none",
    "reportUnusedClass": "none",
    "reportUnusedFunction": "none",
    "reportUnusedVariable": "none",
    "reportDuplicateImport": "error",
    "reportArgumentType": "error",
    "reportAssignmentType": "error",
    "reportReturnType": "error",
    "reportCallIssue": "error",
    "reportIndexIssue": "error",
    "reportOperatorIssue": "error",
    "reportInvalidStringEscapeSequence": "error",
    "stubPath": ""
}